distributaur/__init__.py
distributaur/distributaur.py
distributaur/example/__init__.py
distributaur/example/distributed.py
distributaur/example/local.py
distributaur/example/shared.py
distributaur/example/worker.py
distributaur/tests/__init__.py
distributaur/tests/tests.py
distributaur/tests/worker.py
distributaur-0.0.28.dist-info/LICENSE
distributaur-0.0.28.dist-info/METADATA
distributaur-0.0.28.dist-info/WHEEL
distributaur-0.0.28.dist-info/top_level.txt
distributaur-0.0.28.dist-info/RECORD
