Metadata-Version: 2.1
Name: distributaur
Version: 0.0.28
Summary: Simple task manager and job queue for distributed rendering. Built on celery and redis.
Home-page: https://github.com/RaccoonResearch/distributaur
Author: Raccoon Research
Author-email: team@deepai.org
License: MIT
Classifier: Development Status :: 4 - Beta
Classifier: Intended Audience :: Science/Research
Classifier: License :: OSI Approved :: MIT License
Classifier: Operating System :: POSIX :: Linux
Classifier: Programming Language :: Python :: 3
Classifier: Operating System :: MacOS :: MacOS X
Classifier: Operating System :: Microsoft :: Windows
License-File: LICENSE
Requires-Dist: requests
Requires-Dist: fsspec
Requires-Dist: celery
Requires-Dist: redis
Requires-Dist: huggingface-hub
Requires-Dist: python-dotenv
Requires-Dist: omegaconf
Requires-Dist: tqdm
